README
setup.py
miette/__init__.py
miette/doc.py
miette/exceptions.py
miette.egg-info/PKG-INFO
miette.egg-info/SOURCES.txt
miette.egg-info/dependency_links.txt
miette.egg-info/top_level.txt
miette/cfb/__init__.py
miette/cfb/constants.py
miette/cfb/entry.py
miette/cfb/reader.py